query/__init__.py
query/config.py
query/translate.py
query/utils.py
query_cli-1.0.dist-info/DESCRIPTION.rst
query_cli-1.0.dist-info/METADATA
query_cli-1.0.dist-info/RECORD
query_cli-1.0.dist-info/WHEEL
query_cli-1.0.dist-info/entry_points.txt
query_cli-1.0.dist-info/metadata.json
query_cli-1.0.dist-info/top_level.txt
