Metadata-Version: 2.0
Name: query-cli
Version: 1.0
Summary: This is a simple, yet powerful command line translator with baidu translate
Home-page: UNKNOWN
Author: YangYang
Author-email: zhang-yangyang@foxmail.com
License: MIT
Platform: any
Classifier: Programming Language :: Python :: 2
Classifier: Programming Language :: Python :: 2.6
Classifier: Programming Language :: Python :: 2.7
Classifier: Programming Language :: Python :: 3
Classifier: Programming Language :: Python :: 3.4
Classifier: Programming Language :: Python :: 3.5
Classifier: Programming Language :: Python :: 3.6
Classifier: Programming Language :: Python :: Implementation :: CPython
Classifier: Programming Language :: Python :: Implementation :: PyPy
